sumtree-0.2.7.dist-info/METADATA
sumtree-0.2.7.dist-info/WHEEL
sumtree/py.typed
sumtree/sumtree.pyi
sumtree/__init__.py
sumtree/sumtree.cp39-win32.pyd
sumtree-0.2.7.dist-info/RECORD
