Metadata-Version: 2.1
Name: sumtree
Version: 0.2.7
Classifier: Programming Language :: Rust
Classifier: Programming Language :: Python :: Implementation :: CPython
Classifier: Programming Language :: Python :: Implementation :: PyPy
Summary: Fast and simple SumTree implementation in Rust
Author: Yannick Molinghen <yannick.molinghen@ulb.be>
Author-email: Yannick Molinghen <yannick.molinghen@ulb.be>
Requires-Python: >=3.7
Project-URL: Source Code, https://github.com/yamoling/sumtree
